[{"title": "NM 4 Gengar \u2022 Chinese Dark Crystal Blaze OT \u20b9330 @ zender", "url": "https://nearmint.in/listing/5fd3cdf6-f91e-4128-8b78-b87015043d67"}, {"title": "LP 4 Electivire \u2022 Furious Fists Furious Fists EN \u20b9250 @ zender", "url": "https://nearmint.in/listing/1770beae-9ad0-4c44-9b41-f74359c656ed"}, {"title": "NM 4 Chikorita \u2022 Unseen Forces Unseen Forces EN \u20b9299 @ zender", "url": "https://nearmint.in/listing/5c6b5321-d739-402d-a0e5-efa8a2ef8e26"}, {"title": "NM Mewtwo V-UNION V-Union Set JA \u20b95,500 @ pokehypecards", "url": "https://nearmint.in/listing/39ddc11a-842d-498e-bc69-4571971d1b60"}, {"title": "NM 2 Dodrio \u2022 Classic Collection Japanese Classic: Venusaur JA \u20b9250 @ zender", "url": "https://nearmint.in/listing/362f7ff0-641b-4ee5-b8da-83451ebc4b77"}, {"title": "NM 2 Doduo \u2022 Classic Collection Japanese Classic: Venusaur JA \u20b9250 @ zender", "url": "https://nearmint.in/listing/e09bb7ab-7139-4308-a418-7156631cfa73"}, {"title": "NM 2 Professor Oak Japanese Classic: Blastoise JA \u20b9250 @ zender", "url": "https://nearmint.in/listing/195c3279-0acc-4caf-9636-80d49fc8a4f7"}, {"title": "NM 6 Eeveelutions Mixed LOT - 7 cards bundle OT \u20b9599 @ zender", "url": "https://nearmint.in/listing/af1898c6-a540-4ba0-b63a-f67d0e6c3f22"}, {"title": "AUCTION 2d 2 Wigglytuff Phantasmal Flames EN \u20b9300 opening bid @ pokievault", "url": "https://nearmint.in/listing/f75e034b-1973-4aa1-b38d-057bf95c8ac9"}, {"title": "NM Alakazam ex - \ud6c4\ub518 ex - 065/165 super rare OT \u20b9250 @ drholo", "url": "https://nearmint.in/listing/066abcf4-7a23-47d7-aa0c-f22cee6631ef"}, {"title": "NM N's Zoroark ex - N\uc758 \uc870\ub85c\uc544\ud06c ex - 061/100 Journey Together OT \u20b9200 @ drholo", "url": "https://nearmint.in/listing/b95a26c4-a9fc-45a9-bc4c-7d6c2b72310c"}, {"title": "AUCTION 16h 34m 2 Espathra AR ar OT \u20b949 current bid @ emperors", "url": "https://nearmint.in/listing/a183c75c-073c-4073-a6e8-e75878488636"}, {"title": "AUCTION 16h 18m 2 Bellibolt AR ar OT \u20b950 current bid @ emperors", "url": "https://nearmint.in/listing/7dc5b5fa-d79f-434b-ad71-e492a054f531"}, {"title": "AUCTION 14h 40m 2 Paradise Dragona AR bundle Paradise Dragona JA \u20b9850 current bid @ darshan_", "url": "https://nearmint.in/listing/d202b7aa-4ed1-43ba-aacd-6265cdd56452"}, {"title": "AUCTION 14h 35m 2 Metagross - \u5de8\u91d1\u602a - 209/204 Blade Awakened OT \u20b9500 current bid @ darshan_", "url": "https://nearmint.in/listing/458c0bf6-c890-437b-9455-05676f072121"}, {"title": "NM 2 Ninetales ex (JP) secret rare JA \u20b9800 @ ash", "url": "https://nearmint.in/listing/d36338b2-86cc-4afc-8ca8-d7f1c8caeadf"}, {"title": "NM 2 Team Rocket's Spidops Destined rivals EN \u20b9760 @ jess_tcg", "url": "https://nearmint.in/listing/f4d7cee3-35ce-431a-a22b-0961c460f64f"}, {"title": "NM 3 Team Rocket's Crobat ex Destined rivals EN \u20b9400 @ jess_tcg", "url": "https://nearmint.in/listing/3cf417d5-b68a-434d-852d-8b9d9e0ffc52"}, {"title": "NM 2 Slowpoke Violet ex JA \u20b92,250 @ xaxerous", "url": "https://nearmint.in/listing/5a402ba8-8b60-4eea-a59c-0a54ff95acf8"}, {"title": "NM 2 Alakazam ex Pokemon 151 JA \u20b97,250 @ xaxerous", "url": "https://nearmint.in/listing/02e3eb44-9d8d-4300-be2b-7c6e4bde5659"}]